torchFastText/__init__.py
torchFastText/datasets/__init__.py
torchFastText/datasets/dataset.py
torchFastText/datasets/tokenizer.py
torchFastText/explainability/__init__.py
torchFastText/explainability/visualisation.py
torchFastText/model/__init__.py
torchFastText/model/lightning_module.py
torchFastText/model/losses.py
torchFastText/model/pytorch_model.py
torchFastText/preprocess/__init__.py
torchFastText/preprocess/preprocess.py
torchFastText/torchFastText.py
torchFastText/utilities/__init__.py
torchFastText/utilities/checkers.py
torchFastText/utilities/utils.py
torchfasttext-0.0.5.dist-info/LICENSE
torchfasttext-0.0.5.dist-info/METADATA
torchfasttext-0.0.5.dist-info/WHEEL
torchfasttext-0.0.5.dist-info/RECORD
