Metadata-Version: 2.3
Name: torchFastText
Version: 0.0.5
Summary: An implementation of the https://github.com/facebookresearch/fastText supervised learning algorithm for text classification using Pytorch.
Keywords: fastText,text classification,NLP,automatic coding,deep learning
Author: Tom Seimandi
Author-email: tom.seimandi@gmail.com
Requires-Python: >=3.10
Classifier: Programming Language :: Python :: 3
Classifier: License :: OSI Approved :: MIT License
Classifier: Operating System :: OS Independent
Provides-Extra: explainability
Provides-Extra: preprocess
Requires-Dist: captum ; extra == "explainability"
Requires-Dist: nltk ; extra == "explainability"
Requires-Dist: nltk ; extra == "preprocess"
Requires-Dist: numpy (>=1.26.4)
Requires-Dist: pytorch-lightning (>=2.4.0)
Requires-Dist: unidecode ; extra == "explainability"
Requires-Dist: unidecode ; extra == "preprocess"
